mypydbsimple/__init__.py
mypydbsimple-1.0.1.dist-info/METADATA
mypydbsimple-1.0.1.dist-info/WHEEL
mypydbsimple-1.0.1.dist-info/licenses/LICENSE
mypydbsimple-1.0.1.dist-info/RECORD
